<?xml version="1.0" encoding="utf-8" standalone="yes"?>
<Gesture GesName="a" NumPts="98" Millseconds="3239" Date="Friday, May 22, 2015" TimeOfDay="1:40:57 PM">
  <Point X="0.334918529" Y="-7.4505806E-08" />
  <Point X="0.287961334" Y="-0.031839136" />
  <Point X="0.244172364" Y="-0.07412693" />
  <Point X="0.192109451" Y="-0.10720925" />
  <Point X="0.128996775" Y="-0.117090032" />
  <Point X="0.08761613" Y="-0.155832455" />
  <Point X="0.0371501" Y="-0.179908931" />
  <Point X="-0.0266947616" Y="-0.184296757" />
  <Point X="-0.08932224" Y="-0.194672391" />
  <Point X="-0.1505909" Y="-0.211731672" />
  <Point X="-0.214331672" Y="-0.216896519" />
  <Point X="-0.278136075" Y="-0.221755251" />
  <Point X="-0.3399484" Y="-0.236453131" />
  <Point X="-0.287699848" Y="-0.239964992" />
  <Point X="-0.321798921" Y="-0.256236225" />
  <Point X="-0.280011952" Y="-0.214450046" />
  <Point X="-0.219305232" Y="-0.195775151" />
  <Point X="-0.158738226" Y="-0.176720083" />
  <Point X="-0.112418309" Y="-0.148655772" />
  <Point X="-0.04957951" Y="-0.137398988" />
  <Point X="0.010730736" Y="-0.118169025" />
  <Point X="0.0703269839" Y="-0.0966876745" />
  <Point X="0.125197947" Y="-0.06657231" />
  <Point X="0.1795342" Y="-0.0354799181" />
  <Point X="0.233723134" Y="-0.004172042" />
  <Point X="0.287831962" Y="0.0272529535" />
  <Point X="0.348819435" Y="0.0249055512" />
  <Point X="0.4034333" Y="0.0520220734" />
  <Point X="0.459716558" Y="0.07905652" />
  <Point X="0.4991545" Y="0.0812306851" />
  <Point X="0.535315752" Y="0.118269056" />
  <Point X="0.4990273" Y="0.0840735" />
  <Point X="0.439579129" Y="0.0631787" />
  <Point X="0.377502054" Y="0.0507819541" />
  <Point X="0.315452665" Y="0.06483586" />
  <Point X="0.252251059" Y="0.06890638" />
  <Point X="0.189415753" Y="0.05763327" />
  <Point X="0.126442745" Y="0.0470948778" />
  <Point X="0.06311817" Y="0.0384324156" />
  <Point X="-3.67313623E-05" Y="0.0295597725" />
  <Point X="-0.0274648014" Y="-0.0235606879" />
  <Point X="-0.05489287" Y="-0.07668115" />
  <Point X="-0.110355429" Y="-0.104353935" />
  <Point X="-0.167886689" Y="-0.130148917" />
  <Point X="-0.225891083" Y="-0.154962465" />
  <Point X="-0.2853637" Y="-0.176730752" />
  <Point X="-0.344836324" Y="-0.198499039" />
  <Point X="-0.396736324" Y="-0.229788631" />
  <Point X="-0.437418431" Y="-0.275182933" />
  <Point X="-0.460146" Y="-0.328720242" />
  <Point X="-0.4646843" Y="-0.3662824" />
  <Point X="-0.4070078" Y="-0.3918025" />
  <Point X="-0.347859263" Y="-0.392045915" />
  <Point X="-0.314472049" Y="-0.378991365" />
  <Point X="-0.331283033" Y="-0.3223323" />
  <Point X="-0.351248682" Y="-0.2665229" />
  <Point X="-0.374003351" Y="-0.211572751" />
  <Point X="-0.422080278" Y="-0.181246415" />
  <Point X="-0.462548256" Y="-0.1364973" />
  <Point X="-0.433170885" Y="-0.09906219" />
  <Point X="-0.377676427" Y="-0.07006026" />
  <Point X="-0.320488662" Y="-0.04373179" />
  <Point X="-0.256494969" Y="-0.04194033" />
  <Point X="-0.192501262" Y="-0.04014887" />
  <Point X="-0.128507555" Y="-0.0383574069" />
  <Point X="-0.08136205" Y="0.000216063112" />
  <Point X="-0.03521222" Y="0.04096325" />
  <Point X="0.0217369571" Y="0.0568931065" />
  <Point X="0.08569361" Y="0.05685806" />
  <Point X="0.1442393" Y="0.0806508362" />
  <Point X="0.202998847" Y="0.103728026" />
  <Point X="0.266569346" Y="0.110708609" />
  <Point X="0.325598925" Y="0.0988300443" />
  <Point X="0.380231" Y="0.06817922" />
  <Point X="0.4380517" Y="0.0432459" />
  <Point X="0.448629677" Y="-0.008306924" />
  <Point X="0.424080938" Y="-0.05814713" />
  <Point X="0.4097789" Y="-0.0185227413" />
  <Point X="0.3864285" Y="0.03543367" />
  <Point X="0.3551261" Y="0.08624545" />
  <Point X="0.3195437" Y="0.134821728" />
  <Point X="0.289363444" Y="0.170189545" />
  <Point X="0.2669625" Y="0.15408361" />
  <Point X="0.213860512" Y="0.186924815" />
  <Point X="0.16075854" Y="0.219766021" />
  <Point X="0.107656524" Y="0.252607226" />
  <Point X="0.05455456" Y="0.285448462" />
  <Point X="0.002710376" Y="0.319870263" />
  <Point X="-0.0468693748" Y="0.3570493" />
  <Point X="-0.09552903" Y="0.395255268" />
  <Point X="-0.139633864" Y="0.436696827" />
  <Point X="-0.16795522" Y="0.487990618" />
  <Point X="-0.2099175" Y="0.5297486" />
  <Point X="-0.156894863" Y="0.496799529" />
  <Point X="-0.169117063" Y="0.532545567" />
  <Point X="-0.196018785" Y="0.5858372" />
  <Point X="-0.2386406" Y="0.6079541" />
  <Point X="-0.273289382" Y="0.5635206" />
</Gesture>